dawgie_pydot3-1.0.11.data/data/LICENSE
dawgie_pydot3-1.0.11.data/data/README.md
pydot/__init__.py
pydot/dot_parser.py
dawgie_pydot3-1.0.11.dist-info/LICENSE
dawgie_pydot3-1.0.11.dist-info/METADATA
dawgie_pydot3-1.0.11.dist-info/WHEEL
dawgie_pydot3-1.0.11.dist-info/top_level.txt
dawgie_pydot3-1.0.11.dist-info/RECORD
